odoo/addons/account_invoice_repair_link/README.rst
odoo/addons/account_invoice_repair_link/__init__.py
odoo/addons/account_invoice_repair_link/__manifest__.py
odoo/addons/account_invoice_repair_link/i18n/account_invoice_repair_link.pot
odoo/addons/account_invoice_repair_link/i18n/de.po
odoo/addons/account_invoice_repair_link/i18n/hr.po
odoo/addons/account_invoice_repair_link/i18n/it.po
odoo/addons/account_invoice_repair_link/i18n/pt_BR.po
odoo/addons/account_invoice_repair_link/models/__init__.py
odoo/addons/account_invoice_repair_link/models/account_invoice.py
odoo/addons/account_invoice_repair_link/readme/CONTRIBUTORS.rst
odoo/addons/account_invoice_repair_link/readme/DESCRIPTION.rst
odoo/addons/account_invoice_repair_link/static/description/icon.png
odoo/addons/account_invoice_repair_link/static/description/index.html
odoo/addons/account_invoice_repair_link/tests/__init__.py
odoo/addons/account_invoice_repair_link/tests/test_invoice_repair_link.py
odoo/addons/account_invoice_repair_link/views/account_invoice_views.xml
odoo12_addon_account_invoice_repair_link-12.0.1.0.0.99.dev13.dist-info/METADATA
odoo12_addon_account_invoice_repair_link-12.0.1.0.0.99.dev13.dist-info/WHEEL
odoo12_addon_account_invoice_repair_link-12.0.1.0.0.99.dev13.dist-info/top_level.txt
odoo12_addon_account_invoice_repair_link-12.0.1.0.0.99.dev13.dist-info/RECORD
