Metadata-Version: 2.1
Name: odoo12-addon-account_invoice_repair_link
Version: 12.0.1.0.0.99.dev13
Summary: Adds a link in the invoice to the repair from which it was generated
Home-page: https://github.com/OCA/account-invoicing
Author: Eficent Business and IT Consulting Services S.L.,Odoo Community Association (OCA)
Author-email: support@odoo-community.org
License: AGPL-3
Classifier: Programming Language :: Python
Classifier: Framework :: Odoo
Classifier: Framework :: Odoo :: 12.0
Classifier: License :: OSI Approved :: GNU Affero General Public License v3
Requires-Python: >=3.5
Requires-Dist: odoo<12.1dev,>=12.0a
